buzuai/__init__.py
buzuai/client.py
buzuai-0.1.0.dist-info/licenses/LICENSE
buzuai-0.1.0.dist-info/METADATA
buzuai-0.1.0.dist-info/WHEEL
buzuai-0.1.0.dist-info/top_level.txt
buzuai-0.1.0.dist-info/RECORD
