Metadata-Version: 2.4
Name: buzuai
Version: 0.1.0
Summary: Python client library for BuzuAI chat system via Socket.IO
Author-email: BuzuAI Team <support@buzuai.com>
License: MIT
Project-URL: Homepage, https://github.com/Luisnguyen1/buzuai
Project-URL: Documentation, https://github.com/Luisnguyen1/buzuai#readme
Project-URL: Repository, https://github.com/Luisnguyen1/buzuai
Project-URL: Issues, https://github.com/Luisnguyen1/buzuai/issues
Keywords: buzuai,chatbot,socketio,ai,chat
Classifier: Development Status :: 4 - Beta
Classifier: Intended Audience :: Developers
Classifier: License :: OSI Approved :: MIT License
Classifier: Programming Language :: Python :: 3
Classifier: Programming Language :: Python :: 3.7
Classifier: Programming Language :: Python :: 3.8
Classifier: Programming Language :: Python :: 3.9
Classifier: Programming Language :: Python :: 3.10
Classifier: Programming Language :: Python :: 3.11
Classifier: Programming Language :: Python :: 3.12
Requires-Python: >=3.7
License-File: LICENSE
Requires-Dist: python-socketio[client]>=5.0.0
Dynamic: license-file
Dynamic: requires-python
